FEB1004DATASETS/__init__.py
FEB1004DATASETS/dataset_loader.py
FEB1004DATASETS/data/station_origin_center_1_data.csv
febe1004datasets-0.2.dist-info/LICENCE
febe1004datasets-0.2.dist-info/METADATA
febe1004datasets-0.2.dist-info/WHEEL
febe1004datasets-0.2.dist-info/top_level.txt
febe1004datasets-0.2.dist-info/RECORD
